funlog/__init__.py
funlog/funlog.py
funlog-0.2.1.dist-info/METADATA
funlog-0.2.1.dist-info/WHEEL
funlog-0.2.1.dist-info/entry_points.txt
funlog-0.2.1.dist-info/licenses/LICENSE
funlog-0.2.1.dist-info/RECORD
