Metadata-Version: 2.4
Name: funlog
Version: 0.2.1
Summary: Tiny, useful decorators for logging and tallying function calls
Project-URL: Repository, https://github.com/jlevy/funlog
Author-email: Joshua Levy <joshua@cal.berkeley.edu>
License-Expression: MIT
License-File: LICENSE
Classifier: Development Status :: 4 - Beta
Classifier: Intended Audience :: Developers
Classifier: License :: OSI Approved :: MIT License
Classifier: Operating System :: OS Independent
Classifier: Programming Language :: Python
Classifier: Programming Language :: Python :: 3
Classifier: Programming Language :: Python :: 3.11
Classifier: Programming Language :: Python :: 3.12
Classifier: Programming Language :: Python :: 3.13
Classifier: Typing :: Typed
Requires-Python: <4.0,>=3.10
